<?xml version="1.0" encoding="UTF-8"?>
<!DOCTYPE mapper PUBLIC "-//mybatis.org//DTD Mapper 3.0//EN" "http://mybatis.org/dtd/mybatis-3-mapper.dtd">
<mapper namespace="com.cn.lucky.morning.model.dao.BookInfoMapper">
  <resultMap id="BaseResultMap" type="com.cn.lucky.morning.model.domain.BookInfo">
    <!--
      WARNING - @mbg.generated
      This element is automatically generated by MyBatis Generator, do not modify.
    -->
    <id column="id" jdbcType="BIGINT" property="id" />
    <result column="book_url" jdbcType="VARCHAR" property="bookUrl" />
    <result column="book_source_link" jdbcType="VARCHAR" property="bookSourceLink" />
    <result column="book_source_name" jdbcType="VARCHAR" property="bookSourceName" />
    <result column="book_img" jdbcType="VARCHAR" property="bookImg" />
    <result column="book_img_error" jdbcType="VARCHAR" property="bookImgError" />
    <result column="name" jdbcType="VARCHAR" property="name" />
    <result column="author" jdbcType="VARCHAR" property="author" />
    <result column="novel_des" jdbcType="VARCHAR" property="novelDes" />
    <result column="novel_type" jdbcType="VARCHAR" property="novelType" />
    <result column="last_update" jdbcType="VARCHAR" property="lastUpdate" />
    <result column="last_new" jdbcType="VARCHAR" property="lastNew" />
    <result column="creator_id" jdbcType="BIGINT" property="creatorId" />
  </resultMap>
  <sql id="Example_Where_Clause">
    <!--
      WARNING - @mbg.generated
      This element is automatically generated by MyBatis Generator, do not modify.
    -->
    <where>
      <foreach collection="oredCriteria" item="criteria" separator="or">
        <if test="criteria.valid">
          <trim prefix="(" prefixOverrides="and" suffix=")">
            <foreach collection="criteria.criteria" item="criterion">
              <choose>
                <when test="criterion.noValue">
                  and ${criterion.condition}
                </when>
                <when test="criterion.singleValue">
                  and ${criterion.condition} #{criterion.value}
                </when>
                <when test="criterion.betweenValue">
                  and ${criterion.condition} #{criterion.value} and #{criterion.secondValue}
                </when>
                <when test="criterion.listValue">
                  and ${criterion.condition}
                  <foreach close=")" collection="criterion.value" item="listItem" open="(" separator=",">
                    #{listItem}
                  </foreach>
                </when>
              </choose>
            </foreach>
          </trim>
        </if>
      </foreach>
    </where>
  </sql>
  <sql id="Update_By_Example_Where_Clause">
    <!--
      WARNING - @mbg.generated
      This element is automatically generated by MyBatis Generator, do not modify.
    -->
    <where>
      <foreach collection="example.oredCriteria" item="criteria" separator="or">
        <if test="criteria.valid">
          <trim prefix="(" prefixOverrides="and" suffix=")">
            <foreach collection="criteria.criteria" item="criterion">
              <choose>
                <when test="criterion.noValue">
                  and ${criterion.condition}
                </when>
                <when test="criterion.singleValue">
                  and ${criterion.condition} #{criterion.value}
                </when>
                <when test="criterion.betweenValue">
                  and ${criterion.condition} #{criterion.value} and #{criterion.secondValue}
                </when>
                <when test="criterion.listValue">
                  and ${criterion.condition}
                  <foreach close=")" collection="criterion.value" item="listItem" open="(" separator=",">
                    #{listItem}
                  </foreach>
                </when>
              </choose>
            </foreach>
          </trim>
        </if>
      </foreach>
    </where>
  </sql>
  <sql id="Base_Column_List">
    <!--
      WARNING - @mbg.generated
      This element is automatically generated by MyBatis Generator, do not modify.
    -->
    id, book_url, book_source_link, book_source_name, book_img, book_img_error, name, 
    author, novel_des, novel_type, last_update, last_new, creator_id
  </sql>
  <select id="selectByExample" parameterType="com.cn.lucky.morning.model.domain.BookInfoExample" resultMap="BaseResultMap">
    <!--
      WARNING - @mbg.generated
      This element is automatically generated by MyBatis Generator, do not modify.
    -->
    select
    <if test="distinct">
      distinct
    </if>
    <include refid="Base_Column_List" />
    from m_book_info
    <if test="_parameter != null">
      <include refid="Example_Where_Clause" />
    </if>
    <if test="orderByClause != null">
      order by ${orderByClause}
    </if>
    <if test="limitStart &gt; -1">
      limit ${limitStart} , ${limitEnd}
    </if>
  </select>
  <select id="selectByPrimaryKey" parameterType="java.lang.Long" resultMap="BaseResultMap">
    <!--
      WARNING - @mbg.generated
      This element is automatically generated by MyBatis Generator, do not modify.
    -->
    select 
    <include refid="Base_Column_List" />
    from m_book_info
    where id = #{id,jdbcType=BIGINT}
  </select>
  <delete id="deleteByPrimaryKey" parameterType="java.lang.Long">
    <!--
      WARNING - @mbg.generated
      This element is automatically generated by MyBatis Generator, do not modify.
    -->
    delete from m_book_info
    where id = #{id,jdbcType=BIGINT}
  </delete>
  <delete id="deleteByExample" parameterType="com.cn.lucky.morning.model.domain.BookInfoExample">
    <!--
      WARNING - @mbg.generated
      This element is automatically generated by MyBatis Generator, do not modify.
    -->
    delete from m_book_info
    <if test="_parameter != null">
      <include refid="Example_Where_Clause" />
    </if>
  </delete>
  <insert id="insert" parameterType="com.cn.lucky.morning.model.domain.BookInfo">
    <!--
      WARNING - @mbg.generated
      This element is automatically generated by MyBatis Generator, do not modify.
    -->
    <selectKey keyProperty="id" order="AFTER" resultType="java.lang.Long">
      SELECT LAST_INSERT_ID()
    </selectKey>
    insert into m_book_info (book_url, book_source_link, book_source_name, 
      book_img, book_img_error, name, 
      author, novel_des, novel_type, 
      last_update, last_new, creator_id
      )
    values (#{bookUrl,jdbcType=VARCHAR}, #{bookSourceLink,jdbcType=VARCHAR}, #{bookSourceName,jdbcType=VARCHAR}, 
      #{bookImg,jdbcType=VARCHAR}, #{bookImgError,jdbcType=VARCHAR}, #{name,jdbcType=VARCHAR}, 
      #{author,jdbcType=VARCHAR}, #{novelDes,jdbcType=VARCHAR}, #{novelType,jdbcType=VARCHAR}, 
      #{lastUpdate,jdbcType=VARCHAR}, #{lastNew,jdbcType=VARCHAR}, #{creatorId,jdbcType=BIGINT}
      )
  </insert>
  <insert id="insertSelective" parameterType="com.cn.lucky.morning.model.domain.BookInfo">
    <!--
      WARNING - @mbg.generated
      This element is automatically generated by MyBatis Generator, do not modify.
    -->
    <selectKey keyProperty="id" order="AFTER" resultType="java.lang.Long">
      SELECT LAST_INSERT_ID()
    </selectKey>
    insert into m_book_info
    <trim prefix="(" suffix=")" suffixOverrides=",">
      <if test="bookUrl != null">
        book_url,
      </if>
      <if test="bookSourceLink != null">
        book_source_link,
      </if>
      <if test="bookSourceName != null">
        book_source_name,
      </if>
      <if test="bookImg != null">
        book_img,
      </if>
      <if test="bookImgError != null">
        book_img_error,
      </if>
      <if test="name != null">
        name,
      </if>
      <if test="author != null">
        author,
      </if>
      <if test="novelDes != null">
        novel_des,
      </if>
      <if test="novelType != null">
        novel_type,
      </if>
      <if test="lastUpdate != null">
        last_update,
      </if>
      <if test="lastNew != null">
        last_new,
      </if>
      <if test="creatorId != null">
        creator_id,
      </if>
    </trim>
    <trim prefix="values (" suffix=")" suffixOverrides=",">
      <if test="bookUrl != null">
        #{bookUrl,jdbcType=VARCHAR},
      </if>
      <if test="bookSourceLink != null">
        #{bookSourceLink,jdbcType=VARCHAR},
      </if>
      <if test="bookSourceName != null">
        #{bookSourceName,jdbcType=VARCHAR},
      </if>
      <if test="bookImg != null">
        #{bookImg,jdbcType=VARCHAR},
      </if>
      <if test="bookImgError != null">
        #{bookImgError,jdbcType=VARCHAR},
      </if>
      <if test="name != null">
        #{name,jdbcType=VARCHAR},
      </if>
      <if test="author != null">
        #{author,jdbcType=VARCHAR},
      </if>
      <if test="novelDes != null">
        #{novelDes,jdbcType=VARCHAR},
      </if>
      <if test="novelType != null">
        #{novelType,jdbcType=VARCHAR},
      </if>
      <if test="lastUpdate != null">
        #{lastUpdate,jdbcType=VARCHAR},
      </if>
      <if test="lastNew != null">
        #{lastNew,jdbcType=VARCHAR},
      </if>
      <if test="creatorId != null">
        #{creatorId,jdbcType=BIGINT},
      </if>
    </trim>
  </insert>
  <select id="countByExample" parameterType="com.cn.lucky.morning.model.domain.BookInfoExample" resultType="java.lang.Long">
    <!--
      WARNING - @mbg.generated
      This element is automatically generated by MyBatis Generator, do not modify.
    -->
    select count(*) from m_book_info
    <if test="_parameter != null">
      <include refid="Example_Where_Clause" />
    </if>
  </select>
  <update id="updateByExampleSelective" parameterType="map">
    <!--
      WARNING - @mbg.generated
      This element is automatically generated by MyBatis Generator, do not modify.
    -->
    update m_book_info
    <set>
      <if test="record.id != null">
        id = #{record.id,jdbcType=BIGINT},
      </if>
      <if test="record.bookUrl != null">
        book_url = #{record.bookUrl,jdbcType=VARCHAR},
      </if>
      <if test="record.bookSourceLink != null">
        book_source_link = #{record.bookSourceLink,jdbcType=VARCHAR},
      </if>
      <if test="record.bookSourceName != null">
        book_source_name = #{record.bookSourceName,jdbcType=VARCHAR},
      </if>
      <if test="record.bookImg != null">
        book_img = #{record.bookImg,jdbcType=VARCHAR},
      </if>
      <if test="record.bookImgError != null">
        book_img_error = #{record.bookImgError,jdbcType=VARCHAR},
      </if>
      <if test="record.name != null">
        name = #{record.name,jdbcType=VARCHAR},
      </if>
      <if test="record.author != null">
        author = #{record.author,jdbcType=VARCHAR},
      </if>
      <if test="record.novelDes != null">
        novel_des = #{record.novelDes,jdbcType=VARCHAR},
      </if>
      <if test="record.novelType != null">
        novel_type = #{record.novelType,jdbcType=VARCHAR},
      </if>
      <if test="record.lastUpdate != null">
        last_update = #{record.lastUpdate,jdbcType=VARCHAR},
      </if>
      <if test="record.lastNew != null">
        last_new = #{record.lastNew,jdbcType=VARCHAR},
      </if>
      <if test="record.creatorId != null">
        creator_id = #{record.creatorId,jdbcType=BIGINT},
      </if>
    </set>
    <if test="_parameter != null">
      <include refid="Update_By_Example_Where_Clause" />
    </if>
  </update>
  <update id="updateByExample" parameterType="map">
    <!--
      WARNING - @mbg.generated
      This element is automatically generated by MyBatis Generator, do not modify.
    -->
    update m_book_info
    set id = #{record.id,jdbcType=BIGINT},
      book_url = #{record.bookUrl,jdbcType=VARCHAR},
      book_source_link = #{record.bookSourceLink,jdbcType=VARCHAR},
      book_source_name = #{record.bookSourceName,jdbcType=VARCHAR},
      book_img = #{record.bookImg,jdbcType=VARCHAR},
      book_img_error = #{record.bookImgError,jdbcType=VARCHAR},
      name = #{record.name,jdbcType=VARCHAR},
      author = #{record.author,jdbcType=VARCHAR},
      novel_des = #{record.novelDes,jdbcType=VARCHAR},
      novel_type = #{record.novelType,jdbcType=VARCHAR},
      last_update = #{record.lastUpdate,jdbcType=VARCHAR},
      last_new = #{record.lastNew,jdbcType=VARCHAR},
      creator_id = #{record.creatorId,jdbcType=BIGINT}
    <if test="_parameter != null">
      <include refid="Update_By_Example_Where_Clause" />
    </if>
  </update>
  <update id="updateByPrimaryKeySelective" parameterType="com.cn.lucky.morning.model.domain.BookInfo">
    <!--
      WARNING - @mbg.generated
      This element is automatically generated by MyBatis Generator, do not modify.
    -->
    update m_book_info
    <set>
      <if test="bookUrl != null">
        book_url = #{bookUrl,jdbcType=VARCHAR},
      </if>
      <if test="bookSourceLink != null">
        book_source_link = #{bookSourceLink,jdbcType=VARCHAR},
      </if>
      <if test="bookSourceName != null">
        book_source_name = #{bookSourceName,jdbcType=VARCHAR},
      </if>
      <if test="bookImg != null">
        book_img = #{bookImg,jdbcType=VARCHAR},
      </if>
      <if test="bookImgError != null">
        book_img_error = #{bookImgError,jdbcType=VARCHAR},
      </if>
      <if test="name != null">
        name = #{name,jdbcType=VARCHAR},
      </if>
      <if test="author != null">
        author = #{author,jdbcType=VARCHAR},
      </if>
      <if test="novelDes != null">
        novel_des = #{novelDes,jdbcType=VARCHAR},
      </if>
      <if test="novelType != null">
        novel_type = #{novelType,jdbcType=VARCHAR},
      </if>
      <if test="lastUpdate != null">
        last_update = #{lastUpdate,jdbcType=VARCHAR},
      </if>
      <if test="lastNew != null">
        last_new = #{lastNew,jdbcType=VARCHAR},
      </if>
      <if test="creatorId != null">
        creator_id = #{creatorId,jdbcType=BIGINT},
      </if>
    </set>
    where id = #{id,jdbcType=BIGINT}
  </update>
  <update id="updateByPrimaryKey" parameterType="com.cn.lucky.morning.model.domain.BookInfo">
    <!--
      WARNING - @mbg.generated
      This element is automatically generated by MyBatis Generator, do not modify.
    -->
    update m_book_info
    set book_url = #{bookUrl,jdbcType=VARCHAR},
      book_source_link = #{bookSourceLink,jdbcType=VARCHAR},
      book_source_name = #{bookSourceName,jdbcType=VARCHAR},
      book_img = #{bookImg,jdbcType=VARCHAR},
      book_img_error = #{bookImgError,jdbcType=VARCHAR},
      name = #{name,jdbcType=VARCHAR},
      author = #{author,jdbcType=VARCHAR},
      novel_des = #{novelDes,jdbcType=VARCHAR},
      novel_type = #{novelType,jdbcType=VARCHAR},
      last_update = #{lastUpdate,jdbcType=VARCHAR},
      last_new = #{lastNew,jdbcType=VARCHAR},
      creator_id = #{creatorId,jdbcType=BIGINT}
    where id = #{id,jdbcType=BIGINT}
  </update>
</mapper>